musiclang/__init__.py
musiclang/library.py
musiclang/analyze/__init__.py
musiclang/analyze/chord_inference.py
musiclang/analyze/chord_inference_utils.py
musiclang/analyze/chord_repr_to_chord.py
musiclang/analyze/chroma.py
musiclang/analyze/constants.py
musiclang/analyze/dataset_extractor.py
musiclang/analyze/item.py
musiclang/analyze/load_score.py
musiclang/analyze/midi_parser.py
musiclang/analyze/parser.py
musiclang/analyze/pattern_analyzer.py
musiclang/analyze/pattern_sampler.py
musiclang/analyze/roman_parser.py
musiclang/analyze/score_formatter.py
musiclang/analyze/score_formatter_elements.py
musiclang/analyze/split.py
musiclang/analyze/to_musiclang.py
musiclang/analyze/voice_separation.py
musiclang/analyze/augmented_net/__init__.py
musiclang/analyze/augmented_net/cache.py
musiclang/analyze/augmented_net/chord_vocabulary.py
musiclang/analyze/augmented_net/feature_representation.py
musiclang/analyze/augmented_net/inference.py
musiclang/analyze/augmented_net/input_representations.py
musiclang/analyze/augmented_net/keydistance.py
musiclang/analyze/augmented_net/models.py
musiclang/analyze/augmented_net/output_representations.py
musiclang/analyze/augmented_net/score_parser.py
musiclang/analyze/augmented_net/utils.py
musiclang/predict/__init__.py
musiclang/predict/arranger/__init__.py
musiclang/predict/arranger/arranger.py
musiclang/predict/arranger/arranger_trainer.py
musiclang/predict/arranger/melody_arranger.py
musiclang/predict/arranger/melody_arranger_trainer.py
musiclang/predict/composer/__init__.py
musiclang/predict/composer/auto_composer.py
musiclang/predict/composer/composer.py
musiclang/predict/composer/harmony.py
musiclang/transform/__init__.py
musiclang/transform/base_transformer.py
musiclang/transform/graph.py
musiclang/transform/library.py
musiclang/transform/mask.py
musiclang/transform/merger.py
musiclang/transform/pipeline.py
musiclang/transform/transformer.py
musiclang/transform/utils_random.py
musiclang/transform/chord/__init__.py
musiclang-0.26.0.dist-info/LICENSE.md
musiclang-0.26.0.dist-info/METADATA
musiclang-0.26.0.dist-info/WHEEL
musiclang-0.26.0.dist-info/top_level.txt
musiclang-0.26.0.dist-info/RECORD
