Metadata-Version: 2.1
Name: musiclang
Version: 0.26.0
Summary: A python package for music notation and generation
Author: Florian GARDIN
Author-email: Florian GARDIN <fgardin.pro@gmail.com>
License: BSD 2-Clause License
Project-URL: Homepage, https://github.com/MusicLang/musiclang
Keywords: music,ai,notation
Classifier: License :: OSI Approved :: BSD License
Classifier: Programming Language :: Python
Classifier: Programming Language :: Python :: 3
Requires-Python: >=3.6
License-File: LICENSE.md
Requires-Dist: lxml
Requires-Dist: mido ==1.2.10
Requires-Dist: music21 ==8.1.0
Requires-Dist: numpy
Requires-Dist: pandas ==1.5.3
Requires-Dist: scipy
Requires-Dist: tensorflow
Requires-Dist: toml ==0.10.2
Requires-Dist: tomli ==2.0.1
Requires-Dist: xmlschema ==2.1.1
Requires-Dist: partitura ==1.3.1
Requires-Dist: music21
Requires-Dist: miditok ==2.1.8
Provides-Extra: dev
Requires-Dist: pip-tools ; extra == 'dev'
Requires-Dist: pytest ; extra == 'dev'
